{
  "1": "1\nBarber, Jon He/Him\nMystic Forge Combo\n10-1-0    21-3-0    30    62.66037%    87.50000%    57.33560%\n\n\n2\nCronk, Joshua\nMystic Forge Combo\n10-1-0    21-5-0    30    58.67113%    80.76923%    54.22291%\n3\nWallace, Kelvin\nMystic Forge Combo\n10-1-0    21-5-0    30    50.92319%    80.76923%    50.64200%\n4\nDeresh, Max He/Him\nCephalid Breakfast\n9-0-2    18-4-6    29    70.06428%    71.42857%    60.68578%\n5\nFranklin, AJ He/Him\nDeath and Taxes (Yorion)\n9-0-2    18-3-6    29    63.77411%    74.07407%    57.52421%",
  "2": "1\nJonathon Moore\nMerfolk\n\n8-0-0\n\n\n\n2\nDaniel Sonmerfeld\nView Decklist\n\n8-0-0\n\n\n\n3\nQuincy Huhn\nDomain Zoo\n\n7-1-2000\n\n\n\n4\nIan Mungall\nView Decklist\n\n7-1-2000\n\n\n\n5\nDaniel Genova\nGrinding Breach\n\n7-1-2000\n\n\n\n6\nSeth Fogelsonger\nOrzhov Flicker\n\n7-1-2000\n\n\n\n7\nAnthony Weisz\nView Decklist\n\n7-1-2000\n\n\n\n8\nChris Kral\nBelcher\n\n7-1-2000\n\n\n\n9\nwalker metyko\nBoros Energy\n\n7-1-2000\n\n\n\n10\nNoah Barber\nGrinding Breach\n\n7-1-2000\n\n\n\n11\nRobert W-K\nDimir Ninjas\n\n7-1-2000\n\n\n\n12\nBeau Barnette\nBoros Midrange\n\n7-2-2000\n\n\n\n13\nGabriel Nicholas\nView Decklist\n\n6-1-2001\n\n\n\n14\nSimon Gonzales\nSam Combo\n\n6-1-2001\n\n\n\n15\nLogan Martin\nView Decklist\n\n6-1-2001\n\n\n\n16\nTom Hertfelder\nView Decklist\n\n6-1-2001",
  "3": null,
  "4": null,
  "5": null,
  "6": null,
  "7": null,
  "8": null,
  "9": null,
  "10": null,
  "11": null,
  "12": null,
  "13": null,
  "14": null,
  "15": "1\nBarber, Jon He/Him\nMystic Forge Combo\n10-1-0    21-3-0    30    62.66037%    87.50000%    57.33560%\n2\nCronk, Joshua\nMystic Forge Combo\n10-1-0    21-5-0    30    58.67113%    80.76923%    54.22291%\n3\nWallace, Kelvin\nMystic Forge Combo\n10-1-0    21-5-0    30    50.92319%    80.76923%    50.64200%\n4\nDeresh, Max He/Him\nCephalid Breakfast\n9-0-2    18-4-6    29    70.06428%    71.42857%    60.68578%\n5\nFranklin, AJ He/Him\nDeath and Taxes (Yorion)\n9-0-2    18-3-6    29    63.77411%    74.07407%    57.52421%"
}